GraphPed/__init__.py
GraphPed/_nbdev.py
GraphPed/plot.py
GraphPed-0.0.5.dist-info/LICENSE
GraphPed-0.0.5.dist-info/METADATA
GraphPed-0.0.5.dist-info/WHEEL
GraphPed-0.0.5.dist-info/entry_points.txt
GraphPed-0.0.5.dist-info/top_level.txt
GraphPed-0.0.5.dist-info/RECORD
