Metadata-Version: 2.1
Name: GraphPed
Version: 0.0.5
Summary: A pedigree visualization tool based on dot format and visualized by graphviz
Home-page: https://github.com/changebio/GraphPed/tree/main/
Author: Yin Huang
Author-email: changebio@yeah.net
License: Apache Software License 2.0
Keywords: Complex Pedigrees,Graphviz,Jupiter notebook,Visualization
Platform: UNKNOWN
Classifier: Development Status :: 3 - Alpha
Classifier: Intended Audience :: Developers
Classifier: Natural Language :: English
Classifier: Programming Language :: Python :: 3.6
Classifier: Programming Language :: Python :: 3.7
Classifier: Programming Language :: Python :: 3.8
Classifier: License :: OSI Approved :: Apache Software License
Requires-Python: >=3.6
License-File: LICENSE
Requires-Dist: numpy
Requires-Dist: pandas
Requires-Dist: graphviz
Requires-Dist: IPython
